alysis/__init__.py
alysis/_backend.py
alysis/_constants.py
alysis/_exceptions.py
alysis/_node.py
alysis/_rpc.py
alysis/py.typed
alysis-0.6.2.dist-info/WHEEL
alysis-0.6.2.dist-info/METADATA
alysis-0.6.2.dist-info/licenses/LICENSE.md
alysis-0.6.2.dist-info/RECORD
