Metadata-Version: 2.1
Name: alysis
Version: 0.6.2
Summary: Ethereum testerchain
Author-email: Bogdan Opanchuk <bogdan@opanchuk.net>
Requires-Python: >=3.10
Classifier: Development Status :: 4 - Beta
Classifier: License :: OSI Approved :: MIT License
Classifier: Operating System :: OS Independent
Classifier: Programming Language :: Python :: 3
Requires-Dist: compages>=0.3.0
Requires-Dist: eth-keys>=0.5
Requires-Dist: eth-typing>=5.2
Requires-Dist: eth-utils>=3
Requires-Dist: ethereum-rpc>=0.1
Requires-Dist: py-evm==0.12.1-beta.1
Requires-Dist: rlp>=4
Requires-Dist: setuptools
Provides-Extra: docs
Requires-Dist: sphinx>=4; extra == "docs"
Requires-Dist: furo; extra == "docs"
Requires-Dist: setuptools-scm; extra == "docs"
Provides-Extra: lint
Requires-Dist: mypy>=1.4; extra == "lint"
Requires-Dist: ruff>=0.2; extra == "lint"
Provides-Extra: tests
Requires-Dist: pytest>=6; extra == "tests"
Requires-Dist: pytest-cov; extra == "tests"
Requires-Dist: eth-account>=0.13; extra == "tests"
Project-URL: homepage, https://github.com/fjarri-eth/alysis
